vtt2json/__init__.py
vtt2json/vtt2json.py
vtt2json-0.0.1.dist-info/METADATA
vtt2json-0.0.1.dist-info/WHEEL
vtt2json-0.0.1.dist-info/licenses/LICENSE
vtt2json-0.0.1.dist-info/RECORD
