Metadata-Version: 2.1
Name: vtt2json
Version: 0.0.1
Summary: convert vtt to json
Project-URL: Github, https://github.com/astromech-droid/vtt2csv
Author: astromech-droid
License-File: LICENSE
Classifier: License :: OSI Approved :: MIT License
Classifier: Operating System :: OS Independent
Classifier: Programming Language :: Python :: 3
Requires-Python: >=3.10
